BuildAi/__init__.py
BuildAi/activations.py
BuildAi/nn.py
BuildAi/tensor.py
buildai-0.1.dist-info/METADATA
buildai-0.1.dist-info/WHEEL
buildai-0.1.dist-info/top_level.txt
buildai-0.1.dist-info/RECORD
