Metadata-Version: 2.4
Name: BuildAi
Version: 0.1
Summary: A mini TensorFlow-like library in Python
Home-page: https://github.com/yourusername/aigo
Author: Your Name
Requires-Dist: numpy
Dynamic: author
Dynamic: home-page
Dynamic: requires-dist
Dynamic: summary
